starlaunch/__init__.py
starlaunch/gui.py
starlaunch/lib.py
starlaunch/main.py
starlaunch-1.0.0.dist-info/entry_points.txt
starlaunch-1.0.0.dist-info/WHEEL
starlaunch-1.0.0.dist-info/METADATA
starlaunch-1.0.0.dist-info/RECORD
